README.md
dictondisk.py
setup.py
dictondisk.egg-info/PKG-INFO
dictondisk.egg-info/SOURCES.txt
dictondisk.egg-info/dependency_links.txt
dictondisk.egg-info/top_level.txt