Metadata-Version: 2.1
Name: dictondisk
Version: 1.0
Summary: Implementation of a dictionary in a temporary directory
Home-page: https://github.com/MKuranowski/dictondisk
Author: Mikołaj Kuranowski
Author-email: mkuranowski@gmail.com
License: MIT
Keywords: dictionary dict disk pickle
Platform: UNKNOWN
Classifier: License :: OSI Approved :: MIT License
Classifier: Programming Language :: Python :: 3 :: Only
